nmk_proto/__init__.py
nmk_proto/badges.yml
nmk_proto/files.py
nmk_proto/files.yml
nmk_proto/plugin.yml
nmk_proto/python.py
nmk_proto/python.yml
nmk_proto/templates/__init__.py
nmk_proto/templates/init.py.jinja
nmk_proto-1.2.0.dist-info/licenses/LICENSE
nmk_proto-1.2.0.dist-info/METADATA
nmk_proto-1.2.0.dist-info/WHEEL
nmk_proto-1.2.0.dist-info/top_level.txt
nmk_proto-1.2.0.dist-info/RECORD
