Metadata-Version: 2.4
Name: nmk-proto
Version: 1.2.0
Summary: Code generation plugin from proto files for nmk build system
Author: The dynod project
Maintainer: The dynod project
License: MIT License
Project-URL: Homepage, https://github.com/dynod/nmk-proto
Project-URL: Repository, https://github.com/dynod/nmk-proto
Project-URL: Issues, https://github.com/dynod/nmk/issues?q=is%3Aopen+is%3Aissue+label%3Aplugin%3Aproto
Classifier: Programming Language :: Python :: 3.10
Classifier: Programming Language :: Python :: 3.11
Classifier: Programming Language :: Python :: 3.12
Classifier: Programming Language :: Python :: 3.13
Classifier: Programming Language :: Python :: 3.14
Requires-Python: >=3.10
License-File: LICENSE
Requires-Dist: grpcio
Requires-Dist: protobuf
Requires-Dist: nmk-base
Requires-Dist: Jinja2
Requires-Dist: grpcio-tools
Dynamic: license-file
